stac-1.1.0.dist-info/metadata.json
stac-1.1.0.dist-info/METADATA
stac-1.1.0.dist-info/WHEEL
stac-1.1.0.dist-info/DESCRIPTION.rst
stac-1.1.0.dist-info/zip-safe
stac-1.1.0.dist-info/top_level.txt
stac-1.1.0.dist-info/RECORD
stac/exceptions.py
stac/api.py
stac/util.py
stac/client.py
stac/__init__.py
stac/http.py
